mykoreanromanizer/__init__.py
mykoreanromanizer/enhacer.py
mykoreanromanizer/hangul_romanization_equivalents.py
mykoreanromanizer/romanizer.py
mykoreanromanizer/syllable.py
tests/__init__.py
tests/test_enhacer.py
tests/test_romanizer.py
tests/test_syllable.py
mykoreanromanizer-1.0.1.dist-info/LICENSE.txt
mykoreanromanizer-1.0.1.dist-info/METADATA
mykoreanromanizer-1.0.1.dist-info/WHEEL
mykoreanromanizer-1.0.1.dist-info/top_level.txt
mykoreanromanizer-1.0.1.dist-info/RECORD
