Metadata-Version: 2.1
Name: mykoreanromanizer
Version: 1.0.1
Summary: Korean romanizer based on the Revised Romanization of Korean
Home-page: https://github.com/teresagarcia/my-korean-romanizer
Author: Teresa Garcia
Author-email: teresagar181@gmail.com
License: UNKNOWN
Keywords: Korean,Romanizer
Platform: UNKNOWN
Classifier: Programming Language :: Python :: 3
Classifier: License :: OSI Approved :: MIT License
Classifier: Operating System :: OS Independent
Requires-Python: >=3.6
Requires-Dist: jamo
